shinny_filelock/__init__.py
shinny_filelock/_flockd.py
shinny_filelock-0.0.8.dist-info/LICENSE.txt
shinny_filelock-0.0.8.dist-info/METADATA
shinny_filelock-0.0.8.dist-info/WHEEL
shinny_filelock-0.0.8.dist-info/top_level.txt
shinny_filelock-0.0.8.dist-info/RECORD
