Metadata-Version: 2.1
Name: shinny-filelock
Version: 0.0.8
Summary: A Simple file lock with Context Manager
Author-email: TianQin <tianqincn@gmail.com>
Maintainer-email: Jiachun Tao <taojiachun@shinnytech.com>
License: Apache License
Project-URL: Homepage, https://github.com/shinnytech/shinny-filelock
Project-URL: Bug Reports, https://github.com/shinnytech/shinny-filelock/issues
Project-URL: Source, https://github.com/shinnytech/shinny-filelock
Keywords: lock,context,development
Classifier: Development Status :: 5 - Production/Stable
Classifier: Intended Audience :: Developers
Classifier: License :: OSI Approved :: Apache Software License
Classifier: Programming Language :: Python :: 3
Classifier: Programming Language :: Python :: 3.7
Classifier: Programming Language :: Python :: 3.8
Classifier: Programming Language :: Python :: 3.9
Classifier: Programming Language :: Python :: 3.10
Classifier: Programming Language :: Python :: 3.11
Classifier: Programming Language :: Python :: 3.12
Classifier: Programming Language :: Python :: 3 :: Only
Requires-Python: >=3.9
License-File: LICENSE.txt
Provides-Extra: dev
Provides-Extra: test
